{
    "colors": {
        "cargoLocks": null,
        "date": null,
        "extract": null,
        "name": "colors",
        "passthru": null,
        "pinned": false,
        "src": {
            "name": null,
            "sha256": "sha256-l/RTPZp2v7Y4ffJRT5Fy5Z3TDB4dvWfE7wqMbquXdJA=",
            "type": "url",
            "url": "https://gist.githubusercontent.com/lilydjwg/fdeaf79e921c2f413f44b6f613f6ad53/raw/94d8b2be62657e96488038b0e547e3009ed87d40/colors.py"
        },
        "version": "94d8b2be62657e96488038b0e547e3009ed87d40"
    },
    "double-entry-generator": {
        "cargoLocks": null,
        "date": null,
        "extract": null,
        "name": "double-entry-generator",
        "passthru": {
            "vendorHash": "sha256-Xedva9oGteOnv3rP4Wo3sOHIPyuy2TYwkZV2BAuxY4M="
        },
        "pinned": false,
        "src": {
            "deepClone": false,
            "fetchSubmodules": false,
            "leaveDotGit": false,
            "name": null,
            "owner": "deb-sig",
            "repo": "double-entry-generator",
            "rev": "v2.4.0",
            "sha256": "sha256-XJsectuh2yO4t3nWi0aoBoNNf4AzxXtTmR/e6wrMzKk=",
            "type": "github"
        },
        "version": "v2.4.0"
    },
    "rime_latex": {
        "cargoLocks": null,
        "date": "2023-06-02",
        "extract": null,
        "name": "rime_latex",
        "passthru": null,
        "pinned": false,
        "src": {
            "deepClone": false,
            "fetchSubmodules": false,
            "leaveDotGit": false,
            "name": null,
            "owner": "shenlebantongying",
            "repo": "rime_latex",
            "rev": "fb32dc50c19b3913023199ceaae22168cd5a7db7",
            "sha256": "sha256-ZSnfkHc0yyXZTVZBjPI8mcjR9CRyKy8qpQFww2VF3QI=",
            "type": "github"
        },
        "version": "fb32dc50c19b3913023199ceaae22168cd5a7db7"
    },
    "sway-git-unwrapped": {
        "cargoLocks": null,
        "date": null,
        "extract": null,
        "name": "sway-git-unwrapped",
        "passthru": null,
        "pinned": false,
        "src": {
            "deepClone": false,
            "fetchSubmodules": false,
            "leaveDotGit": false,
            "name": null,
            "owner": "swaywm",
            "repo": "sway",
            "rev": "20ffe545bab3fe518d8d1be00949943f7d39cfe0",
            "sha256": "sha256-2plFvH3747PWHRF8il2FipRG79eXxgzTRpy4A24YHGY=",
            "type": "github"
        },
        "version": "20ffe545bab3fe518d8d1be00949943f7d39cfe0"
    },
    "wlroots-git": {
        "cargoLocks": null,
        "date": "2023-07-12",
        "extract": null,
        "name": "wlroots-git",
        "passthru": null,
        "pinned": false,
        "src": {
            "deepClone": false,
            "fetchSubmodules": false,
            "leaveDotGit": false,
            "name": null,
            "rev": "d8585d661c17cd00d2540be5cbe663bf01c46019",
            "sha256": "sha256-G9yuGuBVjMOWACUkLlfk86PYx/Cdv3hcbe6HXbRF3Jc=",
            "type": "git",
            "url": "https://gitlab.freedesktop.org/wlroots/wlroots.git"
        },
        "version": "d8585d661c17cd00d2540be5cbe663bf01c46019"
    }
}